cloud_os_desktop/AboutDialog.py
cloud_os_desktop/ConnectDialog.py
cloud_os_desktop/EditConnectionDialog.py
cloud_os_desktop/MainWindow.py
cloud_os_desktop/WebBrowser.py
cloud_os_desktop/__init__.py
cloud_os_desktop/app.py
cloud_os_desktop-0.4.2.post3.data/scripts/cloud_os_desktop
cloud_os_desktop-0.4.2.post3.dist-info/LICENSE
cloud_os_desktop-0.4.2.post3.dist-info/METADATA
cloud_os_desktop-0.4.2.post3.dist-info/WHEEL
cloud_os_desktop-0.4.2.post3.dist-info/top_level.txt
cloud_os_desktop-0.4.2.post3.dist-info/RECORD
