Metadata-Version: 2.1
Name: cloud-os-desktop
Version: 0.4.2.post3
Summary: Bayrell OS Desktop Client
Home-page: https://github.com/bayrell-os/desktop_client
Author: Ildar Bikmamatov
Author-email: ildar@bayrell.org
License: Apache License Version 2.0
Keywords: bayrell,bayrell cloud os,bayrell desktop client
Platform: UNKNOWN
Classifier: Environment :: X11 Applications :: Qt
Classifier: License :: OSI Approved :: Apache Software License
Classifier: Operating System :: POSIX :: Linux
Classifier: Operating System :: Microsoft :: Windows :: Windows 10
Classifier: Programming Language :: Python
Classifier: Programming Language :: Python :: 3
Classifier: Programming Language :: Python :: 3.8
Classifier: Topic :: Internet
Classifier: Topic :: System :: Operating System
Classifier: Topic :: Utilities
Requires-Dist: PyNaCl
Requires-Dist: PyQt5
Requires-Dist: PyQtWebEngine
Requires-Dist: paramiko
Requires-Dist: sshtunnel
